zope/app/http/__init__.py
zope/app/http/configure.zcml
zope/app/http/delete.py
zope/app/http/ftesting.zcml
zope/app/http/httpdate.py
zope/app/http/interfaces.py
zope/app/http/options.py
zope/app/http/put.py
zope/app/http/traversal.py
zope/app/http/exception/__init__.py
zope/app/http/exception/configure.zcml
zope/app/http/exception/methodnotallowed.py
zope/app/http/exception/notfound.py
zope/app/http/exception/unauthorized.py
zope/app/http/exception/tests/__init__.py
zope/app/http/exception/tests/test_methodnotallowed.py
zope/app/http/exception/tests/test_unauthorized.py
zope/app/http/tests/__init__.py
zope/app/http/tests/test_delete.py
zope/app/http/tests/test_options.py
zope/app/http/tests/test_put.py
zope/app/http/tests/test_traversers.py
zope_app_http-6.0.dist-info/licenses/LICENSE.txt
zope_app_http-6.0.dist-info/METADATA
zope_app_http-6.0.dist-info/WHEEL
zope_app_http-6.0.dist-info/top_level.txt
zope_app_http-6.0.dist-info/RECORD
