Metadata-Version: 2.4
Name: zope.app.http
Version: 6.0
Summary: HTTP Behavior for the Zope Publisher
Home-page: https://github.com/zopefoundation/zope.app.http
Author: Zope Foundation and Contributors
Author-email: zope-dev@zope.dev
License: ZPL-2.1
Keywords: zope3 http publisher view
Classifier: Development Status :: 5 - Production/Stable
Classifier: Environment :: Web Environment
Classifier: Intended Audience :: Developers
Classifier: License :: OSI Approved :: Zope Public License
Classifier: Programming Language :: Python :: 3
Classifier: Programming Language :: Python :: 3.9
Classifier: Programming Language :: Python :: 3.10
Classifier: Programming Language :: Python :: 3.11
Classifier: Programming Language :: Python :: 3.12
Classifier: Programming Language :: Python :: 3.13
Classifier: Programming Language :: Python :: Implementation
Classifier: Programming Language :: Python :: Implementation :: CPython
Classifier: Programming Language :: Python :: Implementation :: PyPy
Classifier: Natural Language :: English
Classifier: Operating System :: OS Independent
Classifier: Topic :: Internet :: WWW/HTTP
Classifier: Framework :: Zope :: 3
Requires-Python: >=3.9
License-File: LICENSE.txt
Requires-Dist: setuptools
Requires-Dist: zope.interface
Requires-Dist: zope.publisher>=4.0.0a2
Requires-Dist: zope.container>=4.0.0a2
Requires-Dist: zope.filerepresentation
Provides-Extra: test
Requires-Dist: zope.app.wsgi[testlayer]>=4.0; extra == "test"
Requires-Dist: zope.browserpage; extra == "test"
Requires-Dist: zope.component; extra == "test"
Requires-Dist: zope.login; extra == "test"
Requires-Dist: zope.password; extra == "test"
Requires-Dist: zope.principalregistry; extra == "test"
Requires-Dist: zope.securitypolicy>=4.0.0a1; extra == "test"
Requires-Dist: zope.site>=4.0.0a1; extra == "test"
Requires-Dist: zope.testrunner>=6.4; extra == "test"
Dynamic: author
Dynamic: author-email
Dynamic: classifier
Dynamic: description
Dynamic: home-page
Dynamic: keywords
Dynamic: license
Dynamic: license-file
Dynamic: provides-extra
Dynamic: requires-dist
Dynamic: requires-python
Dynamic: summary
